discord/ext/oauth/__init__.py
discord/ext/oauth/client.py
discord/ext/oauth/errors.py
discord/ext/oauth/guild.py
discord/ext/oauth/http.py
discord/ext/oauth/token.py
discord/ext/oauth/user.py
discord_ext_oauth-0.1.0.dist-info/METADATA
discord_ext_oauth-0.1.0.dist-info/WHEEL
discord_ext_oauth-0.1.0.dist-info/top_level.txt
discord_ext_oauth-0.1.0.dist-info/RECORD
