Metadata-Version: 2.1
Name: discord-ext-oauth
Version: 0.1.0
Summary: An asynchronous OAuth2 extension for discord.py.
Home-page: https://github.com/moanie/discord.ext.oauth
Author: moanie
License: MIT
Platform: UNKNOWN
Classifier: License :: OSI Approved :: MIT License
Classifier: Intended Audience :: Developers
Classifier: Natural Language :: English
Classifier: Operating System :: OS Independent
Classifier: Programming Language :: Python :: 3.8
Classifier: Programming Language :: Python :: 3.7
Classifier: Topic :: Internet
Classifier: Topic :: Software Development :: Libraries
Classifier: Topic :: Software Development :: Libraries :: Python Modules
Classifier: Topic :: Utilities
Requires-Python: >=3.7.0
Requires-Dist: aiohttp
Provides-Extra: speedups
Requires-Dist: aiohttp[speedups] ; extra == 'speedups'
